lbr_context
