Metadata-Version: 2.1
Name: lbr-context
Version: 0.1.0
Summary: A context manager for custom resources
Home-page: https://github.com/trek10inc/LBR-Context-Manager
Author: Trek10, Inc
Author-email: package-management@trek10.com
License: MIT
Platform: UNKNOWN
